text_summarizer/__init__.py
text_summarizer/cli.py
text_summarizer/summarizer.py
text_summarizer/ui.py
text_summarizer/data/tennis.csv
text_summarizer_aweebtaku-1.2.3.dist-info/licenses/LICENSE
text_summarizer_aweebtaku-1.2.3.dist-info/METADATA
text_summarizer_aweebtaku-1.2.3.dist-info/WHEEL
text_summarizer_aweebtaku-1.2.3.dist-info/entry_points.txt
text_summarizer_aweebtaku-1.2.3.dist-info/top_level.txt
text_summarizer_aweebtaku-1.2.3.dist-info/RECORD
